CHANGES.txt
DEPENDENCES.txt
README.txt
setup.py
src/ng/__init__.py
src/ng.xmlrpcscan.egg-info/PKG-INFO
src/ng.xmlrpcscan.egg-info/SOURCES.txt
src/ng.xmlrpcscan.egg-info/dependency_links.txt
src/ng.xmlrpcscan.egg-info/entry_points.txt
src/ng.xmlrpcscan.egg-info/namespace_packages.txt
src/ng.xmlrpcscan.egg-info/not-zip-safe
src/ng.xmlrpcscan.egg-info/requires.txt
src/ng.xmlrpcscan.egg-info/top_level.txt
src/ng/xmlrpcscan/__init__.py
src/ng/xmlrpcscan/configure.zcml
src/ng/xmlrpcscan/ng.xmlrpcscan.txt
src/ng/xmlrpcscan/ngxmlrpcscan.py
src/ng/xmlrpcscan/browser/__init__.py
src/ng/xmlrpcscan/browser/configure.zcml
src/ng/xmlrpcscan/browser/xmlrpcedit.py
src/ng/xmlrpcscan/etc/ng.xmlrpcscan-configure.zcml
