Metadata-Version: 1.0
Name: ng.xmlrpcscan
Version: 0.0.6
Summary: Program used to scan zope3 tree and execute data by external (console) program
Home-page: http://www.dreambot.ru/dreamdotzope3releases/ng.xmlrpcscan
Author: Andrey Orlov
Author-email: dbdt@dreambot.ru
License: GPL v2.1
Platform: UNKNOWN
Classifier: Environment :: Web Environment
Classifier: Intended Audience :: Developers
Classifier: License :: OSI Approved :: GNU General Public License (GPL)
Classifier: Programming Language :: Python
Classifier: Operating System :: OS Independent
Classifier: Topic :: Internet :: WWW/HTTP
Classifier: Framework :: Zope3
